LICENSE
README.md
setup.py
src/__init__.py
src/kerkle/__init__.py
src/kerkle.egg-info/PKG-INFO
src/kerkle.egg-info/SOURCES.txt
src/kerkle.egg-info/dependency_links.txt
src/kerkle.egg-info/not-zip-safe
src/kerkle.egg-info/requires.txt
src/kerkle.egg-info/top_level.txt
src/kerkle/core/__init__.py
src/kerkle/core/helping.py
src/kerkle/core/proofing.py
src/kerkle/core/storing.py
src/kerkle/core/treeing.py
tests/test_tree.py