Metadata-Version: 2.1
Name: kerkle
Version: 0.0.1
Summary: A KERI Event Sparse Merkle Tree
Home-page: https://github.com/WebOfTrust/sparse-kerkle-tree
Author: Phil Feairheller
Author-email: phil@healthKERI.com
License: Apache Software License 2.0
Project-URL: Documentation, https://kerkle.readthedocs.io/
Project-URL: Changelog, https://kerkle.readthedocs.io/en/latest/changelog.html
Project-URL: Issue Tracker, https://github.com/WebOfTrust/sparse-kerkle-tree/issues
Classifier: Development Status :: 3 - Alpha
Classifier: Intended Audience :: Developers
Classifier: License :: OSI Approved :: Apache Software License
Classifier: Operating System :: Unix
Classifier: Operating System :: POSIX
Classifier: Operating System :: Microsoft :: Windows
Classifier: Programming Language :: Python :: 3.12
Classifier: Programming Language :: Python :: Implementation :: CPython
Classifier: Topic :: Utilities
Requires-Python: >=3.12.2
License-File: LICENSE
Requires-Dist: keri>=1.2.0-dev10
Requires-Dist: lmdb>=1.4.1
Requires-Dist: pysodium>=0.7.17
Requires-Dist: blake3>=0.4.1
